texttospeech_sundar/__init__.py
texttospeech_sundar/tts.py
texttospeech_sundar-1.0.5.dist-info/licenses/LICENSE
texttospeech_sundar-1.0.5.dist-info/METADATA
texttospeech_sundar-1.0.5.dist-info/WHEEL
texttospeech_sundar-1.0.5.dist-info/top_level.txt
texttospeech_sundar-1.0.5.dist-info/RECORD
