Metadata-Version: 2.4
Name: texttospeech-sundar
Version: 1.0.5
Summary: Hybrid online+offline text-to-speech package
Author: Sundarapandi T
License: MIT License
Project-URL: Homepage, https://pypi.org/project/texttospeech-sundar/
Requires-Python: >=3.8
License-File: LICENSE
Requires-Dist: gtts
Requires-Dist: pygame
Requires-Dist: pyttsx3
Dynamic: license-file
